plaidcloud/utilities/__init__.py
plaidcloud/utilities/analyze_table.py
plaidcloud/utilities/bom.py
plaidcloud/utilities/clean_files.py
plaidcloud/utilities/color.py
plaidcloud/utilities/connect.py
plaidcloud/utilities/convert_encoding.py
plaidcloud/utilities/converter.py
plaidcloud/utilities/data_helpers.py
plaidcloud/utilities/frame_manager.py
plaidcloud/utilities/hasher.py
plaidcloud/utilities/network_helpers.py
plaidcloud/utilities/pretty_size.py
plaidcloud/utilities/query.py
plaidcloud/utilities/sql_expression.py
plaidcloud/utilities/sqlalchemy_functions.py
plaidcloud/utilities/sqlalchemy_views.py
plaidcloud/utilities/stringtransforms.py
plaidcloud/utilities/udf.py
plaidcloud/utilities/udf_utility_loader.py
plaidcloud/utilities/utility.py
plaidcloud/utilities/xlwings_utility.py
plaidcloud/utilities/xray.py
plaidcloud/utilities/remote/dim_helpers.py
plaidcloud/utilities/remote/dimension.py
plaidcloud/utilities/tests/__init__.py
plaidcloud/utilities/tests/test_clean_files.py
plaidcloud/utilities/tests/test_frame_manager.py
plaidcloud/utilities/tests/test_hasher.py
plaidcloud/utilities/tests/test_remote_dimension.py
plaidcloud/utilities/tests/test_sql_expression.py
plaidcloud/utilities/tests/test_sqlalchemy_functions.py
plaidcloud/utilities/tests/test_sqlalchemy_views.py
plaidcloud/utilities/udf_helpers/__init__.py
plaidcloud_utilities-1.8.22.dist-info/licenses/LICENSE
plaidcloud_utilities-1.8.22.dist-info/METADATA
plaidcloud_utilities-1.8.22.dist-info/WHEEL
plaidcloud_utilities-1.8.22.dist-info/top_level.txt
plaidcloud_utilities-1.8.22.dist-info/RECORD
