Metadata-Version: 2.4
Name: plaidcloud-utilities
Version: 1.8.22
Summary: PlaidCloud Common Utilities for PlaidLink, PlaidXL and Custom Transforms
Author-email: Michael Rea <mike@plaidcloud.com>, Paul Morel <paul@plaidcloud.com>
Maintainer-email: Pat Buxton <pat@plaidcloud.com>, Charlie Laymon <charlie@plaidcloud.com>, Simon Moscrop <simon@plaidcloud.com>
License-Expression: Apache-2.0
Project-URL: Homepage, https://plaidcloud.com
Project-URL: Documentation, https://docs.plaidcloud.com
Project-URL: Repository, https://github.com/PlaidCloud/plaid-utilities.git
Project-URL: Issues, https://github.com/PlaidCloud/plaid-utilities/issues
Keywords: plaidcloud,utilities
Classifier: Development Status :: 5 - Production/Stable
Classifier: Programming Language :: Python :: 3
Classifier: Programming Language :: Python :: 3.10
Classifier: Programming Language :: Python :: 3.11
Classifier: Programming Language :: Python :: 3.12
Classifier: Programming Language :: Python :: 3.13
Classifier: Programming Language :: Python :: 3.14
Requires-Python: >=3.10
License-File: LICENSE
Requires-Dist: argparse
Requires-Dist: chardet
Requires-Dist: fastavro
Requires-Dist: fastparquet
Requires-Dist: ipython
Requires-Dist: numpy
Requires-Dist: pandas<3.0.0
Requires-Dist: plaidcloud-rpc>=1.6.1
Requires-Dist: PyYAML
Requires-Dist: requests
Requires-Dist: setuptools
Requires-Dist: orjson
Requires-Dist: SQLAlchemy
Requires-Dist: texttable
Requires-Dist: toolz
Requires-Dist: xlwings; platform_system == "Windows"
Provides-Extra: test
Requires-Dist: pytest; extra == "test"
Requires-Dist: mock; extra == "test"
Requires-Dist: minimock; extra == "test"
Requires-Dist: pyarrow; extra == "test"
Requires-Dist: pytest-cov; extra == "test"
Requires-Dist: pytest-runner; extra == "test"
Requires-Dist: sqlalchemy-greenplum; extra == "test"
Requires-Dist: starrocks; extra == "test"
Requires-Dist: databend_sqlalchemy; extra == "test"
Provides-Extra: full
Requires-Dist: plaidcloud-rpc[full]>=1.6.3; extra == "full"
Dynamic: license-file
